e2b_mcp/__init__.py
e2b_mcp/__main__.py
e2b_mcp/cli.py
e2b_mcp/models.py
e2b_mcp/runner.py
e2b_mcp/version.py
e2b_mcp-0.2.0.dist-info/METADATA
e2b_mcp-0.2.0.dist-info/WHEEL
e2b_mcp-0.2.0.dist-info/entry_points.txt
e2b_mcp-0.2.0.dist-info/licenses/LICENSE
e2b_mcp-0.2.0.dist-info/RECORD
