Metadata-Version: 2.4
Name: e2b-mcp
Version: 0.2.0
Summary: Run MCP (Model Context Protocol) servers securely in E2B sandboxes
Project-URL: Homepage, https://github.com/cased/e2b-mcp
Project-URL: Repository, https://github.com/cased/e2b-mcp
Project-URL: Documentation, https://github.com/cased/e2b-mcp#readme
Project-URL: Bug Tracker, https://github.com/cased/e2b-mcp/issues
Author-email: Cased <team@cased.com>
License: MIT
License-File: LICENSE
Keywords: ai,e2b,mcp,sandbox,security,tools
Classifier: Development Status :: 4 - Beta
Classifier: Intended Audience :: Developers
Classifier: License :: OSI Approved :: MIT License
Classifier: Programming Language :: Python :: 3
Classifier: Programming Language :: Python :: 3.10
Classifier: Programming Language :: Python :: 3.11
Classifier: Programming Language :: Python :: 3.12
Classifier: Topic :: Scientific/Engineering :: Artificial Intelligence
Classifier: Topic :: Security
Classifier: Topic :: Software Development :: Libraries :: Python Modules
Requires-Python: >=3.10
Requires-Dist: click>=8.0.0
Requires-Dist: e2b-code-interpreter>=1.5.1
Provides-Extra: dev
Requires-Dist: black>=23.0.0; extra == 'dev'
Requires-Dist: mypy>=1.0.0; extra == 'dev'
Requires-Dist: pytest-asyncio>=0.21.0; extra == 'dev'
Requires-Dist: pytest>=7.0.0; extra == 'dev'
Requires-Dist: ruff>=0.1.0; extra == 'dev'
